colorich/__init__.py
colorich/main.py
colorich-0.6.5.dist-info/METADATA
colorich-0.6.5.dist-info/WHEEL
colorich-0.6.5.dist-info/top_level.txt
colorich-0.6.5.dist-info/RECORD
