Metadata-Version: 2.1
Name: colorich
Version: 0.6.5
Summary: Replace the classic print function with several colorful functions
Author: Ethan Amar
Author-email: EthanA120@Gmail.com
Requires-Dist: requests>=2.32.3
